beetsplug/__init__.py
beetsplug/extendedmetadata.py
beetsplug/emd/__init__.py
beetsplug/emd/audiofilefields.py
beetsplug/emd/metadata.py
beetsplug/emd/query.py
beetsplug/emd/command/__init__.py
beetsplug/emd/command/action.py
beetsplug/emd/command/actions/__init__.py
beetsplug/emd/command/actions/add_action.py
beetsplug/emd/command/actions/confirmation_action.py
beetsplug/emd/command/actions/copy_action.py
beetsplug/emd/command/actions/delete_action.py
beetsplug/emd/command/actions/rename_action.py
beetsplug/emd/command/actions/show_action.py
beetsplug/emd/command/actions/update_action.py
beets_extended_metadata-0.3.1.dist-info/LICENSE
beets_extended_metadata-0.3.1.dist-info/METADATA
beets_extended_metadata-0.3.1.dist-info/WHEEL
beets_extended_metadata-0.3.1.dist-info/top_level.txt
beets_extended_metadata-0.3.1.dist-info/RECORD
