Metadata-Version: 2.1
Name: beets-extended-metadata
Version: 0.3.1
Summary: beets plugin to use custom, extended metadata
Home-page: https://github.com/calne-ca/beets-plugin-extended-metadata
Author: Joscha Düringer
Author-email: joscha.dueringer@beardbot.net
License: MIT
Platform: ALL
Classifier: Topic :: Multimedia :: Sound/Audio
Classifier: Topic :: Multimedia :: Sound/Audio :: Players :: MP3
Classifier: License :: OSI Approved :: MIT License
Classifier: Environment :: Console
Classifier: Programming Language :: Python :: 3
Classifier: Programming Language :: Python :: 3.4
Classifier: Programming Language :: Python :: 3.5
Classifier: Programming Language :: Python :: 3.6
Classifier: Programming Language :: Python :: 3.7
Requires-Dist: beets (>=1.4.9)
Requires-Dist: mediafile (>=0.9.0)
Provides-Extra: build
Requires-Dist: wheel ; extra == 'build'
Requires-Dist: twine ; extra == 'build'
Provides-Extra: test
Requires-Dist: pytest ; extra == 'test'
Requires-Dist: mockito ; extra == 'test'
Requires-Dist: testcontainers ; extra == 'test'
